README.md
setup.py
document_your_code.egg-info/PKG-INFO
document_your_code.egg-info/SOURCES.txt
document_your_code.egg-info/dependency_links.txt
document_your_code.egg-info/entry_points.txt
document_your_code.egg-info/requires.txt
document_your_code.egg-info/top_level.txt
dyc/__init__.py
dyc/base.py
dyc/classes.py
dyc/diff.py
dyc/dyc.py
dyc/events.py
dyc/exceptions.py
dyc/hooks.py
dyc/main.py
dyc/methods.py
dyc/parser.py
dyc/top.py
dyc/utils.py
dyc/configs/__init__.py
dyc/configs/defaults.yaml
tests/__init__.py
tests/test_classes.py
tests/test_utils.py