Metadata-Version: 2.1
Name: document-your-code
Version: 0.4.0
Summary: UNKNOWN
Home-page: https://github.com/Zarad1993/dyc
Author: Mohammad Albakri
Author-email: mohammad.albakri93@gmail.com
License: UNKNOWN
Platform: UNKNOWN
